flexivdrdk/__init__.py
flexivdrdk/flexivdrdk.cpython-312-aarch64-linux-gnu.so
flexivdrdk.libs/libassimp-8dfddbf8.so.5.2.0
flexivdrdk.libs/libdraco-34fe7218.so.4.0.0
flexivdrdk.libs/libminizip-f27e8edf.so.1.0.0
flexivdrdk-1.1.0.dist-info/METADATA
flexivdrdk-1.1.0.dist-info/WHEEL
flexivdrdk-1.1.0.dist-info/top_level.txt
flexivdrdk-1.1.0.dist-info/RECORD
flexivdrdk-1.1.0.dist-info/licenses/LICENSE
