Metadata-Version: 2.4
Name: flexivdrdk
Version: 1.1.0
Summary: Flexiv Dual Robot Development Kit (DRDK)
Author: Flexiv Ltd.
Author-email: business@flexiv.com
License: Apache-2.0
Requires-Python: >=3.8
License-File: LICENSE
Dynamic: author
Dynamic: author-email
Dynamic: description
Dynamic: license
Dynamic: license-file
Dynamic: requires-python
Dynamic: summary
